zope.app.apidoc-5.0-py3.11-nspkg.pth
zope/app/apidoc/README.rst
zope/app/apidoc/__init__.py
zope/app/apidoc/apidoc.py
zope/app/apidoc/classregistry.py
zope/app/apidoc/classregistry.rst
zope/app/apidoc/component.py
zope/app/apidoc/component.rst
zope/app/apidoc/configure.zcml
zope/app/apidoc/disabled.py
zope/app/apidoc/disabled.zcml
zope/app/apidoc/enabled.zcml
zope/app/apidoc/ftesting-base.zcml
zope/app/apidoc/ftesting.zcml
zope/app/apidoc/interface.py
zope/app/apidoc/interface.rst
zope/app/apidoc/interfaces.py
zope/app/apidoc/meta.zcml
zope/app/apidoc/presentation.py
zope/app/apidoc/presentation.rst
zope/app/apidoc/static.py
zope/app/apidoc/static.zcml
zope/app/apidoc/test.zcml
zope/app/apidoc/testing.py
zope/app/apidoc/tests.py
zope/app/apidoc/utilities.py
zope/app/apidoc/utilities.rst
zope/app/apidoc/bookmodule/__init__.py
zope/app/apidoc/bookmodule/book.py
zope/app/apidoc/bookmodule/book.zcml
zope/app/apidoc/bookmodule/browser.py
zope/app/apidoc/bookmodule/chapter.pt
zope/app/apidoc/bookmodule/configure.zcml
zope/app/apidoc/bookmodule/empty.txt
zope/app/apidoc/bookmodule/intro.txt
zope/app/apidoc/bookmodule/menu.pt
zope/app/apidoc/bookmodule/meta.zcml
zope/app/apidoc/bookmodule/metaconfigure.py
zope/app/apidoc/bookmodule/metadirectives.py
zope/app/apidoc/bookmodule/static_menu.pt
zope/app/apidoc/bookmodule/tests.py
zope/app/apidoc/browser/README.rst
zope/app/apidoc/browser/__init__.py
zope/app/apidoc/browser/apidoc.css
zope/app/apidoc/browser/apidoc.py
zope/app/apidoc/browser/configure.zcml
zope/app/apidoc/browser/contents.pt
zope/app/apidoc/browser/details_macros.pt
zope/app/apidoc/browser/disabled.pt
zope/app/apidoc/browser/disabled.zcml
zope/app/apidoc/browser/favicon.png
zope/app/apidoc/browser/harrow.png
zope/app/apidoc/browser/index.pt
zope/app/apidoc/browser/macros.py
zope/app/apidoc/browser/menu.pt
zope/app/apidoc/browser/menu_macros.pt
zope/app/apidoc/browser/modules.pt
zope/app/apidoc/browser/nodevmode.rst
zope/app/apidoc/browser/notfound.pt
zope.app.apidoc-5.0.dist-info/LICENSE.txt
zope.app.apidoc-5.0.dist-info/METADATA
zope.app.apidoc-5.0.dist-info/WHEEL
zope.app.apidoc-5.0.dist-info/entry_points.txt
zope.app.apidoc-5.0.dist-info/namespace_packages.txt
zope.app.apidoc-5.0.dist-info/top_level.txt
zope.app.apidoc-5.0.dist-info/RECORD
