Metadata-Version: 2.1
Name: zope.app.apidoc
Version: 5.0
Summary: API Documentation and Component Inspection for Zope 3
Home-page: http://github.com/zopefoundation/zope.app.apidoc
Author: Zope Corporation and Contributors
Author-email: zope-dev@zope.org
License: ZPL 2.1
Keywords: zope3 api documentation
Classifier: Development Status :: 5 - Production/Stable
Classifier: Environment :: Web Environment
Classifier: Intended Audience :: Developers
Classifier: License :: OSI Approved :: Zope Public License
Classifier: Programming Language :: Python
Classifier: Programming Language :: Python :: 3
Classifier: Programming Language :: Python :: 3.7
Classifier: Programming Language :: Python :: 3.8
Classifier: Programming Language :: Python :: 3.9
Classifier: Programming Language :: Python :: 3.10
Classifier: Programming Language :: Python :: 3.11
Classifier: Programming Language :: Python :: Implementation :: CPython
Classifier: Programming Language :: Python :: Implementation :: PyPy
Classifier: Natural Language :: English
Classifier: Operating System :: OS Independent
Classifier: Topic :: Internet :: WWW/HTTP
Classifier: Framework :: Zope :: 3
License-File: LICENSE.txt
Requires-Dist: persistent
Requires-Dist: ZODB
Requires-Dist: setuptools
Requires-Dist: zope.annotation
Requires-Dist: zope.app.appsetup (>=4.0.0)
Requires-Dist: zope.app.basicskin (>=4.0.0)
Requires-Dist: zope.app.exception (>=4.0.0)
Requires-Dist: zope.app.onlinehelp (>=4.0.1)
Requires-Dist: zope.app.preference (>=4.0.0)
Requires-Dist: zope.app.publisher (>=4.0.0)
Requires-Dist: zope.app.renderer (>=4.1.0)
Requires-Dist: zope.app.tree (>=4.0.0)
Requires-Dist: zope.cachedescriptors
Requires-Dist: zope.component (>=3.8.0)
Requires-Dist: zope.configuration
Requires-Dist: zope.container
Requires-Dist: zope.deprecation
Requires-Dist: zope.hookable
Requires-Dist: zope.i18n
Requires-Dist: zope.interface
Requires-Dist: zope.location (>=4.0.3)
Requires-Dist: zope.proxy
Requires-Dist: zope.publisher (>=4.3.1)
Requires-Dist: zope.schema
Requires-Dist: zope.security (>=4.1.1)
Requires-Dist: zope.site
Requires-Dist: zope.testbrowser
Requires-Dist: zope.testing
Requires-Dist: zope.traversing (>=4.1.0)
Provides-Extra: docs
Requires-Dist: repoze.sphinx.autointerface ; extra == 'docs'
Requires-Dist: sphinx ; extra == 'docs'
Requires-Dist: sphinx-rtd-theme ; extra == 'docs'
Requires-Dist: sphinxcontrib-programoutput (>=0.11) ; extra == 'docs'
Provides-Extra: static
Requires-Dist: zope.app.authentication (>=4.0.0) ; extra == 'static'
Requires-Dist: zope.app.folder (>=4.0.0) ; extra == 'static'
Requires-Dist: zope.app.http (>=4.0.1) ; extra == 'static'
Requires-Dist: zope.app.principalannotation (>=4.0.0) ; extra == 'static'
Requires-Dist: zope.app.rotterdam (>=4.0.1) ; extra == 'static'
Requires-Dist: zope.app.wsgi (>=4.1.0) ; extra == 'static'
Requires-Dist: zope.applicationcontrol (>=4.0.0) ; extra == 'static'
Requires-Dist: zope.browserpage (>=4.1.0) ; extra == 'static'
Requires-Dist: zope.login ; extra == 'static'
Requires-Dist: zope.principalannotation ; extra == 'static'
Requires-Dist: zope.securitypolicy ; extra == 'static'
Requires-Dist: zope.testing ; extra == 'static'
Requires-Dist: zope.testrunner ; extra == 'static'
Requires-Dist: zope.app.component[test] ; extra == 'static'
Requires-Dist: zope.app.form[test] ; extra == 'static'
Requires-Dist: zope.app.schema[test] ; extra == 'static'
Provides-Extra: test
Requires-Dist: zope.app.authentication (>=4.0.0) ; extra == 'test'
Requires-Dist: zope.app.folder (>=4.0.0) ; extra == 'test'
Requires-Dist: zope.app.http (>=4.0.1) ; extra == 'test'
Requires-Dist: zope.app.principalannotation (>=4.0.0) ; extra == 'test'
Requires-Dist: zope.app.rotterdam (>=4.0.1) ; extra == 'test'
Requires-Dist: zope.app.wsgi (>=4.1.0) ; extra == 'test'
Requires-Dist: zope.applicationcontrol (>=4.0.0) ; extra == 'test'
Requires-Dist: zope.browserpage (>=4.1.0) ; extra == 'test'
Requires-Dist: zope.login ; extra == 'test'
Requires-Dist: zope.principalannotation ; extra == 'test'
Requires-Dist: zope.securitypolicy ; extra == 'test'
Requires-Dist: zope.testing ; extra == 'test'
Requires-Dist: zope.testrunner ; extra == 'test'
Requires-Dist: zope.app.component[test] ; extra == 'test'
Requires-Dist: zope.app.form[test] ; extra == 'test'
Requires-Dist: zope.app.schema[test] ; extra == 'test'
